uhw/__init__.py
uhw/parser.py
uhw/protocol.py
uhw/server.py
uhw-0.0.2.dist-info/LICENSE
uhw-0.0.2.dist-info/METADATA
uhw-0.0.2.dist-info/WHEEL
uhw-0.0.2.dist-info/top_level.txt
uhw-0.0.2.dist-info/RECORD
