Metadata-Version: 2.1
Name: uhw
Version: 0.0.2
Summary: Lightweight asynchronous command parsing and serving framework.
License: BSD 3-Clause License
Project-URL: homepage, https://github.com/mcpcpc/uhw
Project-URL: repository, https://github.com/mcpcpc/uhw
Requires-Python: >=3.11
License-File: LICENSE
Provides-Extra: dev
Requires-Dist: black ; extra == 'dev'
Requires-Dist: coverage ; extra == 'dev'
